QCustomPlot2.cpython-39-x86_64-linux-gnu.so
QCustomPlot2-2.1.1.1.dist-info/WHEEL
QCustomPlot2-2.1.1.1.dist-info/METADATA
QCustomPlot2-2.1.1.1.dist-info/RECORD
