Metadata-Version: 2.1
Name: QCustomPlot2
Version: 2.1.1.1
Requires-Python: >=3.7
Summary: QCustomPlot is a Qt widget for plotting and data visualization
Home-Page: https://github.com/salsergey/QCustomPlot2-PyQt5
Maintainer: Sergey Salnikov
Maintainer-Email: salsergey@gmail.com
License: MIT
Classifier: Development Status :: 5 - Production/Stable
Classifier: Environment :: X11 Applications :: Qt
Classifier: Intended Audience :: Developers
Classifier: License :: OSI Approved :: MIT License
Classifier: Operating System :: POSIX :: Linux
Classifier: Operating System :: Microsoft :: Windows
Classifier: Programming Language :: Python :: 2
Classifier: Programming Language :: Python :: 2.7
Classifier: Programming Language :: Python :: 3
Classifier: Programming Language :: Python :: 3.3
Classifier: Programming Language :: Python :: 3.4
Classifier: Programming Language :: Python :: 3.5
Classifier: Programming Language :: Python :: 3.6
Classifier: Programming Language :: Python :: 3.7
Classifier: Programming Language :: Python :: 3.8
Classifier: Programming Language :: Python :: 3.9
Classifier: Programming Language :: Python :: 3.10
Classifier: Programming Language :: Python :: 3.11
Classifier: Topic :: Software Development :: User Interfaces
Requires-Dist: PyQt5
